serverside/__init__.py
serverside/admin.py
serverside/apps.py
serverside/models.py
serverside/signals.py
serverside/utils.py
serverside/backends/__init__.py
serverside/backends/base.py
serverside/backends/postgresql/__init__.py
serverside/backends/postgresql/user.py
serverside/migrations/0001_initial.py
serverside/migrations/__init__.py
django_serverside-22.3.65.dist-info/LICENSE
django_serverside-22.3.65.dist-info/METADATA
django_serverside-22.3.65.dist-info/WHEEL
django_serverside-22.3.65.dist-info/top_level.txt
django_serverside-22.3.65.dist-info/RECORD
