Metadata-Version: 2.1
Name: django-serverside
Version: 22.3.65
Summary: Django app for adding users to a database.
Home-page: https://github.com/woernerm/django-serverside
Author: Marcus Wörner
Author-email: woernerm@protonmail.com
License: UNKNOWN
Project-URL: Bug Tracker, https://github.com/woernerm/django-serverside/issues
Platform: UNKNOWN
Classifier: Programming Language :: Python :: 3
Classifier: License :: OSI Approved :: Apache Software License
Classifier: Topic :: Software Development :: Libraries :: Python Modules
Classifier: Operating System :: OS Independent
Classifier: Intended Audience :: Developers
Classifier: Natural Language :: English
Requires-Python: >=3.7
License-File: LICENSE
Requires-Dist: psycopg2
Requires-Dist: Django
